multirun/__init__.py
multirun/core.py
multirun/importer.py
multirun/main.py
pymultirun-0.1.0.dist-info/METADATA
pymultirun-0.1.0.dist-info/WHEEL
pymultirun-0.1.0.dist-info/entry_points.txt
pymultirun-0.1.0.dist-info/RECORD
