Metadata-Version: 2.4
Name: pymultirun
Version: 0.1.0
Summary: A multi-process runtime library with health checks
Project-URL: Homepage, https://github.com/vvanglro/pymultirun
Author-email: vvanglro <vvanglro@gmail.com>
License-Expression: MIT
Requires-Python: >=3.9
Requires-Dist: click>=8.1.8
